{
    "_key_id": 300031,
    "_id": 14375,
    "name": "endpoint",
    "description": "sadfsdf",
    "event_handlers": [
        {
            "_id": 12828,
            "name": "state-to-kv",
            "event": "js-after-presence",
            "channels": "chat-engine-jquery-kitchen-sink",
            "file": "js-after-presence/state-to-kv.js",
            "output": "blocks-output-zs7XiDOUAVUX7TJyfZyc.1491244110678036"
        },
        {
            "_id": 12830,
            "name": "get-kv-state",
            "event": "js-on-rest",
            "file": "js-on-rest/get-kv-state.js",
            "output": "blocks-output-zs7XiDOUAVUX7TJyfZyc.3378024893952203"
        }
    ]
}
